Workbook

Sheet Company Definition
A1: BUDGET
A3: Product | B3: Price | C3: Quantity | D3: Maintenance/unit | E3: Annual cost | F3: Type | G3: Time window | H3: Amortization | J3: Role | K3: Quantity | L3: Yearly gross salary | M3: Yearly salary cost | N3: Total
A4: Microsoft Windows 11 | B4: 0 | C4: 2 | D4: 0 | E4: =B4*C4*12 -> 0 | F4: Amortization | G4: 4 | H4: =E4*0.3333 -> 0 | J4: Team Leader | K4: 1 | L4: 45000 | M4: =L4+(L4*0.322) -> 59490 | N4: =M4 -> 59490
A5: Microsoft Office 365 | B5: 10 | C5: 2 | D5: 0 | E5: =B5*C5*12 -> 240 | F5: Subscription | G5: Monthly | H5: 0 | J5: Data Engineer | K5: 1 | L5: 35000 | M5: =L5+(L5*0.322) -> 46270 | N5: =M5 -> 46270
A6: Microsoft Project 2016 | B6: 59.9 | C6: 1 | D6: 0 | E6: =B6/G6 -> 14.975 | F6: Amortization | G6: 4 | H6: =B6*0.3333*0.25 -> 4.9911675 | J6: Junior Developer | K6: 1 | L6: 24000 | M6: =L6+(L6*0.322) -> 31728 | N6: =M6 -> 31728
A7: Claude Code | B7: 20 | C7: 1 | D7: 0 | E7: =B7*C7*12 -> 240 | F7: Subscription | G7: Monthly | H7: 0 | J7: Project Leader | K7: 1 | L7: 53300 | M7: =L7+(L7*0.322) -> 70462.6 | N7: =M7 -> 70462.6
A8: PyCharm Pro | B8: 13.19 | C8: 1 | D8: 0 | E8: =B8*C8*12 -> 158.28 | F8: Subscription | G8: Monthly | H8: 0 | J8: Total | N8: =SUM(N4:N7) -> 207950.6
A9: MongoDB Atlas | B9: 0 | C9: 1 | D9: 0 | E9: =B9*C9*12 -> 0 | F9: Subscription | G9: 4 | H9: =E9*0.3333*0.25 -> 0
A10: Vercel | B10: 0 | C10: 1 | D10: 0 | E10: =B10*C10*12 -> 0 | F10: Subscription | G10: 4 | H10: =E10*0.3333*0.25 -> 0 | J10: Role | K10: Total | L10: Prod (%) | M10: Direct cost | N10: CI (%) | O10: Indirect cost | R10: Concept | S10: Cost
A11: GitHub | B11: 0 | C11: 1 | D11: 0 | E11: =B11*C11*12 -> 0 | F11: Subscription | G11: 4 | H11: =E11*0.3333*0.25 -> 0 | J11: Team Leader | K11: =N4 -> 59490 | L11: 0.65 | M11: =K11*L11 -> 38668.5 | N11: =100%-L11 -> 0.35 | O11: =K11*N11 -> 20821.5 | R11: Total direct costs | S11: =M15 -> 122959.22
A12: Docker Desktop | B12: 0 | C12: 1 | D12: 0 | E12: 0 | F12: Amortization | G12: 4 | H12: =E12*0.3333*0.25 -> 0 | J12: Data Engineer | K12: =N5 -> 46270 | L12: 0.9 | M12: =K12*L12 -> 41643 | N12: =100%-L12 -> 0.1 | O12: =K12*N12 -> 4627 | R12: Total indirect costs | S12: =O15+C33+E15 -> 107184.14
A13: Google AI Studio | B13: 0 | C13: 1 | D13: 0 | E13: 0 | F13: Subscription | G13: 4 | H13: =E13*0.3333*0.25 -> 0 | J13: Junior Developer | K13: =N6 -> 31728 | L13: 0.9 | M13: =K13*L13 -> 28555.2 | N13: =100%-L13 -> 0.1 | O13: =K13*N13 -> 3172.8 | R13: Total costs | S13: =S11+S12 -> 230143.36
A14: HP ENVY 17-da0000ns (Includes Windows License) | B14: =1599*C14 -> 3198 | C14: 2 | D14: 100 | E14: =(B14+(D14*C14))/G14 -> 849.5 | F14: Amortization | G14: 4 | H14: =(B14+(D14*C14))*0.25*0.3333 -> 283.13835 | J14: Project Leader | K14: =N7 -> 70462.6 | L14: 0.2 | M14: =K14*L14 -> 14092.52 | N14: =100%-L14 -> 0.8 | O14: =K14*N14 -> 56370.08 | R14: Target benefits (25%) | S14: =0.25*S13 -> 57535.839
A15: Total | E15: =SUM(E4:E14) -> 1502.755 | J15: Total | M15: =SUM(M11:M14) -> 122959.22 | O15: =SUM(O11:O14) -> 84991.38 | R15: Billing needs | S15: =S14+S13 -> 287679.19
R16: Billing based on productive hours | S16: =M22 -> 287679.19
J17: Role | K17: Prod. Hours/yr | L17: Price/hour | M17: Billing | N17: Price/hour (w/o benefits) | R17: Total costs-billing margin | S17: =((S16-S15)/S15)*100 -> 0
A18: Service | B18: Monthly cost | C18: Anual cost | H18: 1750 | J18: Team Leader | K18: =H18*L11 -> 1137.5 | L18: =N18*1.25 -> 71.38346 | M18: =L18*K18 -> 81198.685 | N18: =(M4/H18)+N$25 -> 57.106768
A19: Office cleaning | B19: 120 | C19: 1440 | H19: 1750 | J19: Data Engineer | K19: =H19*L12 -> 1575 | L19: =N19*1.25 -> 61.940602 | M19: =L19*K19 -> 97556.449 | N19: =(M5/H19)+N$25 -> 49.552482
A20: Office rent | B20: 650 | C20: =B20*12 -> 7800 | H20: 1750 | J20: Junior Developer | K20: =H20*L13 -> 1575 | L20: =N20*1.25 -> 51.55346 | M20: =L20*K20 -> 81196.699 | N20: =(M6/H20)+N$25 -> 41.242768
A21: Office supplies | B21: 60 | C21: =B21*12 -> 720 | H21: 1750 | J21: Project Leader | K21: =H21*L14 -> 350 | L21: =N21*1.25 -> 79.221031 | M21: =L21*K21 -> 27727.361 | N21: =(M7/H21)+N$25 -> 63.376825
A22: Electricity & climate control | B22: 95 | C22: =B22*12 -> 1140 | J22: Total | K22: =SUM(K18:K21) -> 4637.5 | M22: =SUM(M18:M21) -> 287679.19
A23: Water expenses | B23: 20 | C23: 240
A24: Waste tax | B24: 0 | C24: 150
A25: Transport | B25: 200 | C25: 2400 | M25: Overhead | N25: =S12/K22 -> 23.112482
A26: Audits | B26: 125 | C26: 1500
A27: Fiber Internet | B27: 70 | C27: 840
A28: Accounting and payroll services | B28: 160 | C28: 1920
A29: Insurance | B29: 0 | C29: 500
A30: Hardware maintenance | B30: 25 | C30: 300
A31: Security and alarm system | B31: 45 | C31: 540
A32: Communication costs | B32: 100 | C32: =B32*12 -> 1200
A33: Total | B33: =SUM(B19:B32) -> 1670 | C33: =SUM(C19:C32) -> 20690

Sheet Detailed Budget
B3: I1 | C3: I2 | D3: I3 | E3: Description | F3: Quantity | G3: Units | H3: Price | I3: Subtotal | J3: Total | M3: Task | N3: Cost
B4: 01 | E4: Sprint 1: Analysis and planning | F4: 106 | G4: Hours | J4: =SUM(I5:I28) -> 5421.7791 | M4: =E4 -> Sprint 1: Analysis and planning | N4: =J4*1.25 -> 6777.2239
C5: 001 | E5: Project planning | F5: 8 | G5: Hours | I5: =H6*F5 -> 456.85414 | M5: =E29 -> Sprint 2: System design | N5: =J29*1.25 -> 5309.7035
D6: 01 | E6: Team Leader | G6: Hours | H6: ='Company Definition'!N$18 -> 57.106768 | M6: =E46 -> Sprint 3: Backend & pipeline development | N6: =J46*1.25 -> 4095.7911
C7: 002 | E7: Project budgeting | F7: 8 | G7: Hours | I7: =H8*F7 -> 456.85414 | M7: =E59 -> Sprint 4: Full NLP pipeline implementation | N7: =J59*1.25 -> 4622.4774
D8: 01 | E8: Team Leader | G8: Hours | H8: ='Company Definition'!N$18 -> 57.106768 | M8: =E76 -> Sprint 5: Data visualizations and web application aspects | N8: =J76*1.25 -> 3918.0629
C9: 003 | E9: Literature research (topic modeling, BERT, classification…) | F9: 10 | G9: Hours | I9: =H10*F9 -> 571.06768 | M9: =E89 -> Sprint 6: Final documentation & product refinements | N9: =J89*1.25 -> 2216.7988
D10: 01 | E10: Team Leader | G10: Hours | H10: ='Company Definition'!N$18 -> 57.106768 | M10: Fortnightly meetings | N10: =J96*1.25 -> 4425.7291
C11: 004 | E11: ActEU paper research | F11: 10 | G11: Hours | I11: =H12*F11 -> 571.06768 | M11: Subtotal | N11: =SUM(N4:N10) -> 31365.787
D12: 01 | E12: Team Leader | G12: Hours | H12: ='Company Definition'!N$18 -> 57.106768 | M12: VAT (21%) | N12: =N11*0.21 -> 6586.8152
C13: 005 | E13: Similar theses research | F13: 10 | G13: Hours | I13: =H14*F13 -> 571.06768 | M13: Total (+ VAT) | N13: =N11*1.21 -> 37952.602
D14: 01 | E14: Team Leader | G14: Hours | H14: ='Company Definition'!N$18 -> 57.106768
C15: 006 | E15: Dataset understanding (format, metadata…) | F15: 8 | G15: Hours | I15: =H16*F15 -> 396.41986
D16: 01 | E16: Data Engineer | G16: Hours | H16: ='Company Definition'!N$19 -> 49.552482
C17: 007 | E17: Research of alternatives | F17: 8 | G17: Hours | I17: =H18*F17 -> 329.94214
D18: 01 | E18: Junior Developer | G18: Hours | H18: ='Company Definition'!N$20 -> 41.242768
C19: 008 | E19: Use case developing | F19: 8 | G19: Hours | I19: =H20*F19 -> 329.94214
D20: 01 | E20: Junior Developer | G20: Hours | H20: ='Company Definition'!N$20 -> 41.242768
C21: 009 | E21: Overall technological decisions | F21: 8 | G21: Hours | I21: =H22*F21 -> 456.85414
D22: 01 | E22: Team Leader | G22: Hours | H22: ='Company Definition'!N$18 -> 57.106768
C23: 010 | E23: Project requirements | F23: 8 | G23: Hours | I23: =H24*F23 -> 456.85414
D24: 01 | E24: Team Leader | G24: Hours | H24: ='Company Definition'!N$18 -> 57.106768
C25: 011 | E25: Interface mock-ups | F25: 8 | G25: Hours | I25: =H26*F25 -> 329.94214
D26: 01 | E26: Junior Developer | G26: Hours | H26: ='Company Definition'!N$20 -> 41.242768
C27: 012 | E27: Documentation (Chapters 2 & 4) | F27: 12 | G27: Hours | I27: =H28*F27 -> 494.91321
D28: 01 | E28: Junior Developer | G28: Hours | H28: ='Company Definition'!N$20 -> 41.242768
B29: 02 | E29: Sprint 2: System design | F29: 84 | G29: Hours | J29: =SUM(I30:I45) -> 4247.7628
C30: 001 | E30: Data processing pipeline design | F30: 8 | G30: Hours | I30: =H31*F30 -> 396.41986
D31: 01 | E31: Data Engineer | G31: Hours | H31: ='Company Definition'!N$19 -> 49.552482
C32: 002 | E32: Web system architecture design | F32: 10 | G32: Hours | I32: =H33*F32 -> 571.06768
D33: 01 | E33: Team Leader | G33: Hours | H33: ='Company Definition'!N$18 -> 57.106768
C34: 003 | E34: Testing strategy | F34: 12 | G34: Hours | I34: =H35*F34 -> 685.28121
C35: 004 | D35: 01 | E35: Team Leader | G35: Hours | H35: ='Company Definition'!N$18 -> 57.106768
E36: Database design | F36: 8 | G36: Hours | I36: =H37*F36 -> 396.41986
C37: 005 | D37: 01 | E37: Data Engineer | G37: Hours | H37: ='Company Definition'!N$19 -> 49.552482
E38: Class design | F38: 10 | G38: Hours | I38: =H39*F38 -> 713.8346
C39: 006 | D39: 01 | E39: Team Leader | G39: Hours | H39: ='Company Definition'!L$18 -> 71.38346
C40: 007 | D40: 01 | E40: Tech stack sandboxing | F40: 6 | G40: Hours | I40: =H41*F40 -> 247.45661
E41: Junior Developer | G41: Hours | H41: ='Company Definition'!N$20 -> 41.242768
C42: 008 | D42: 01 | E42: Documentation (Chapter 5) | F42: 20 | G42: Hours | I42: =H43*F42 -> 824.85535
E43: Junior Developer | G43: Hours | H43: ='Company Definition'!N$20 -> 41.242768
C44: 009 | D44: 01 | E44: Github setup | F44: 10 | G44: Hours | I44: =H45*F44 -> 412.42768
E45: Junior Developer | G45: Hours | H45: ='Company Definition'!N$20 -> 41.242768
B46: 03 | E46: Sprint 3: Backend & pipeline development | F46: 73 | G46: Hours | J46: =SUM(I47:I58) -> 3276.6329
C47: 001 | E47: Main backend functionalities | F47: 8 | G47: Hours | I47: =H48*F47 -> 329.94214
D48: 01 | E48: Junior Developer | G48: Hours | H48: ='Company Definition'!N$20 -> 41.242768
C49: 002 | E49: Database deployment & faceted search functionalities | F49: 8 | G49: Hours | I49: =H50*F49 -> 396.41986
D50: 01 | E50: Data Engineer | G50: Hours | H50: ='Company Definition'!N$19 -> 49.552482
C51: 003 | E51: Document retrieval based on user query | F51: 10 | G51: Hours | I51: =H52*F51 -> 495.52482
D52: 01 | E52: Data Engineer | G52: Hours | H52: ='Company Definition'!N$19 -> 49.552482
C53: 004 | E53: Unit testing | F53: 8 | G53: Hours | I53: =H54*F53 -> 329.94214
D54: 01 | E54: Junior Developer | G54: Hours | H54: ='Company Definition'!N$20 -> 41.242768
C55: 005 | E55: Initial topic modeling mock with specific cases | F55: 14 | G55: Hours | I55: =H56*F55 -> 693.73475
D56: 01 | E56: Data Engineer | G56: Hours | H56: ='Company Definition'!N$19 -> 49.552482
C57: 006 | D57: 01 | E57: Documentation (Chapters 3 & 6) | F57: 25 | G57: Hours | I57: =H58*F57 -> 1031.0692
E58: Junior Developer | G58: Hours | H58: ='Company Definition'!N$20 -> 41.242768
B59: 04 | E59: Sprint 4: Full NLP pipeline implementation | F59: 81 | G59: Hours | J59: =SUM(I60:I75) -> 3697.9819
C60: 001 | E60: LLM reconciliation of specific use case topics | F60: 6 | G60: Hours | I60: =H61*F60 -> 297.31489
D61: 01 | E61: Data Engineer | G61: Hours | H61: ='Company Definition'!N$19 -> 49.552482
C62: 002 | E62: Topic generation for any query | F62: 12 | I62: =H63*F62 -> 594.62978
D63: 01 | E63: Data Engineer | H63: ='Company Definition'!N$19 -> 49.552482
C64: 003 | E64: Unit testing | F64: 8 | I64: =H65*F64 -> 329.94214
D65: 01 | E65: Junior Developer | H65: ='Company Definition'!N$20 -> 41.242768
C66: 004 | E66: Human topic confirmation functionality | F66: 4 | I66: =H67*F66 -> 164.97107
D67: 01 | E67: Junior Developer | H67: ='Company Definition'!N$20 -> 41.242768
C68: 005 | E68: Classificator training based on validated topics functionality | F68: 10 | I68: =H69*F68 -> 495.52482
D69: 01 | E69: Data Engineer | H69: ='Company Definition'!N$19 -> 49.552482
C70: 006 | E70: Dataset labeling through classificator functionality | F70: 15 | I70: =H71*F70 -> 743.28723
D71: 01 | E71: Data Engineer | H71: ='Company Definition'!N$19 -> 49.552482
C72: 007 | E72: Unit testing | F72: 10 | I72: =H73*F72 -> 412.42768
D73: 01 | E73: Junior Developer | H73: ='Company Definition'!N$20 -> 41.242768
C74: 008 | E74: Documentation (Chapters 8, 9) | F74: 16 | I74: =H75*F74 -> 659.88428
D75: 01 | E75: Junior Developer | H75: ='Company Definition'!N$20 -> 41.242768
B76: 05 | E76: Sprint 5: Data visualizations and web application aspects | F76: 76 | J76: =SUM(I77:I88) -> 3134.4503
C77: 001 | E77: Narrative trend visualizations | F77: 8 | I77: =H78*F77 -> 329.94214
D78: 01 | E78: Junior Developer | H78: ='Company Definition'!N$20 -> 41.242768
C79: 002 | E79: WAF configuration & other security aspects | F79: 10 | I79: =H80*F79 -> 412.42768
D80: 01 | E80: Junior Developer | H80: ='Company Definition'!N$20 -> 41.242768
C81: 003 | E81: Web application refinements | F81: 15 | I81: =H82*F81 -> 618.64151
D82: 01 | E82: Junior Developer | H82: ='Company Definition'!N$20 -> 41.242768
C83: 004 | E83: Usability tests | F83: 10 | I83: =H84*F83 -> 412.42768
D84: 01 | E84: Junior Developer | H84: ='Company Definition'!N$20 -> 41.242768
C85: 005 | E85: Deployment | F85: 8 | I85: =H86*F85 -> 329.94214
D86: 01 | E86: Junior Developer | H86: ='Company Definition'!N$20 -> 41.242768
C87: 006 | E87: Documentation (Chapters 9, 10 & 11) | F87: 25 | I87: =H88*F87 -> 1031.0692
D88: 01 | E88: Junior Developer | H88: ='Company Definition'!N$20 -> 41.242768
B89: 06 | E89: Sprint 6: Final documentation & product refinements | F89: 43 | J89: =SUM(I90:I95) -> 1773.439
C90: 001 | E90: Documentation (Chapters 1, 12 & 13) | F90: 25 | I90: =H91*F90 -> 1031.0692
D91: 01 | E91: Junior Developer | H91: ='Company Definition'!N$20 -> 41.242768
C92: 002 | E92: Frontend refinements | F92: 10 | I92: =H93*F92 -> 412.42768
D93: 01 | E93: Junior Developer | H93: ='Company Definition'!N$20 -> 41.242768
C94: 003 | E94: Usability tests | F94: 8 | I94: =H95*F94 -> 329.94214
D95: 01 | E95: Junior Developer | H95: ='Company Definition'!N$20 -> 41.242768
B96: 07 | E96: Fortnightly meeting | F96: 8 | J96: =SUM(I97:I120) -> 3540.5833
C97: 001 | E97: Meeting 1 | F97: 1 | I97: =(H98+H99)*F97 -> 98.349535
D98: 01 | E98: Junior Developer | H98: ='Company Definition'!N$20 -> 41.242768
D99: 02 | E99: Project Leader | H99: ='Company Definition'!N$18 -> 57.106768
C100: 002 | E100: Meeting 2 | F100: 2 | I100: =(H101+H102)*F100 -> 196.69907
D101: 03 | E101: Junior Developer | H101: ='Company Definition'!N$20 -> 41.242768
D102: 04 | E102: Project Leader | H102: ='Company Definition'!N$18 -> 57.106768
...
